lb/nightly/functions/__init__.py
lb/nightly/functions/build.py
lb/nightly/functions/build_log.py
lb/nightly/functions/checkout.py
lb/nightly/functions/common.py
lb/nightly/functions/data/Makefile-cmake.mk
lb/nightly/functions/data/Makefile-cmt-common.mk
lb/nightly/functions/data/Makefile-cmt.mk
lb/nightly/functions/data/Makefile-common.mk
lb/nightly/functions/data/cmake/BinaryTagUtils.cmake
lb/nightly/functions/data/cmake/CMakeFunctionalUtils.cmake
lb/nightly/functions/data/cmake/GangaTools.cmake
lb/nightly/functions/data/cmake/GaudiBuildFlags.cmake
lb/nightly/functions/data/cmake/GaudiCPackSettings.cmake
lb/nightly/functions/data/cmake/GaudiDefaultToolchain.cmake
lb/nightly/functions/data/cmake/GaudiProjectConfig.cmake
lb/nightly/functions/data/cmake/GaudiToolchainMacros.cmake
lb/nightly/functions/data/cmake/HEPToolsMacros.cmake
lb/nightly/functions/data/cmake/InheritHEPTools.cmake
lb/nightly/functions/data/cmake/Instrument.cmake
lb/nightly/functions/data/cmake/LHCbFindPackage.cmake
lb/nightly/functions/data/cmake/LegacyGaudiCMakeSupport.cmake
lb/nightly/functions/data/cmake/README.md
lb/nightly/functions/data/cmake/UseHEPTools.cmake
lb/nightly/functions/data/cmake/cpack_install.cmake
lb/nightly/functions/data/cmake/externals.cmake
lb/nightly/functions/data/cmake/gaudi-clang-format-8
lb/nightly/functions/data/cmake/instrument_func.cmake.in
lb/nightly/functions/data/cmake/modules/EnableROOT5.cmake
lb/nightly/functions/data/cmake/modules/EnableROOT6.cmake
lb/nightly/functions/data/cmake/modules/FindAIDA.cmake
lb/nightly/functions/data/cmake/modules/FindCASTOR.cmake
lb/nightly/functions/data/cmake/modules/FindCLHEP.cmake
lb/nightly/functions/data/cmake/modules/FindCOOL.cmake
lb/nightly/functions/data/cmake/modules/FindCORAL.cmake
lb/nightly/functions/data/cmake/modules/FindCppUnit.cmake
lb/nightly/functions/data/cmake/modules/FindEigen.cmake
lb/nightly/functions/data/cmake/modules/FindFFTW.cmake
lb/nightly/functions/data/cmake/modules/FindFastJet.cmake
lb_nightly_functions-0.4.0.dist-info/entry_points.txt
lb_nightly_functions-0.4.0.dist-info/LICENSE
lb_nightly_functions-0.4.0.dist-info/WHEEL
lb_nightly_functions-0.4.0.dist-info/METADATA
lb_nightly_functions-0.4.0.dist-info/RECORD
